packageupload/__init__.py
packageupload/command_line.py
packageupload-1.5.2.dist-info/LICENSE
packageupload-1.5.2.dist-info/METADATA
packageupload-1.5.2.dist-info/WHEEL
packageupload-1.5.2.dist-info/entry_points.txt
packageupload-1.5.2.dist-info/top_level.txt
packageupload-1.5.2.dist-info/RECORD
