Metadata-Version: 2.1
Name: packageupload
Version: 1.5.2
Summary: The most easy way to upload your packages to PyPI!
Home-page: https://github.com/Animenosekai/packageupload
Author: Anime no Sekai
Author-email: niichannomail@gmail.com
License: MIT
Download-URL: https://github.com/Animenosekai/packageupload/archive/v1.3.tar.gz
Keywords: package,packageupload,upload,pip,pypi,pypiupload,animenosekai,python
Platform: UNKNOWN
Classifier: Development Status :: 4 - Beta
Classifier: License :: OSI Approved :: MIT License
Classifier: Programming Language :: Python :: 3
Classifier: Programming Language :: Python :: 3.4
Classifier: Programming Language :: Python :: 3.5
Classifier: Programming Language :: Python :: 3.6
Classifier: Programming Language :: Python :: 3.7
Classifier: Programming Language :: Python :: 3.8
Requires-Dist: setuptools
Requires-Dist: twine
Requires-Dist: lifeeasy
Requires-Dist: filecenter
